{
  "resourceType" : "ValueSet",
  "id" : "68a156ce-9d6b-4f83-a28b-22826665893d-170",
  "url" : "http://hl7.org/fhir/comparison/ValueSet/68a156ce-9d6b-4f83-a28b-22826665893d-170",
  "name" : "UnionSmokingStatusTypeAndLOINCCodes",
  "title" : "Union of Smoking Status Type And LOINC Codes",
  "status" : "active",
  "date" : "2024-10-09T04:26:54+00:00",
  "jurisdiction" : [{
    "coding" : [{
      "system" : "urn:iso:std:iso:3166",
      "code" : "US"
    }]
  }],
  "compose" : {
    "include" : [{
      "valueSet" : ["http://cts.nlm.nih.gov/fhir/ValueSet/2.16.840.1.113762.1.4.1267.4"]
    },
    {
      "valueSet" : ["http://cts.nlm.nih.gov/fhir/ValueSet/2.16.840.1.113762.1.4.1267.5"]
    },
    {
      "system" : "http://loinc.org"
    }]
  }
}